pwmg/__init__.py
pwmg/pwmg.py
pwmg-0.0.7.dist-info/LICENSE
pwmg-0.0.7.dist-info/METADATA
pwmg-0.0.7.dist-info/WHEEL
pwmg-0.0.7.dist-info/entry_points.txt
pwmg-0.0.7.dist-info/top_level.txt
pwmg-0.0.7.dist-info/RECORD
