Metadata-Version: 2.1
Name: pwmg
Version: 0.0.7
Summary: A password management tool
Home-page: https://github.com/fredxia/pwmg
Author: Fred Xia
Author-email: fredxia2011@gmail.com
Classifier: Programming Language :: Python :: 3
Classifier: License :: OSI Approved :: MIT License
Classifier: Operating System :: OS Independent
Requires-Python: >=3.6
License-File: LICENSE
